{"trial_id": "0268", "hyperparameters": {"space": [{"class_name": "Choice", "config": {"name": "activation", "default": "relu", "conditions": [], "values": ["relu", "tanh", "sigmoid"], "ordered": false}}, {"class_name": "Int", "config": {"name": "first_units", "default": null, "conditions": [], "min_value": 10, "max_value": 150, "step": 2, "sampling": "linear"}}, {"class_name": "Int", "config": {"name": "num_layers", "default": null, "conditions": [], "min_value": 1, "max_value": 6, "step": 1, "sampling": "linear"}}, {"class_name": "Int", "config": {"name": "units_0", "default": null, "conditions": [], "min_value": 1, "max_value": 150, "step": 6, "sampling": "linear"}}, {"class_name": "Int", "config": {"name": "units_1", "default": null, "conditions": [], "min_value": 1, "max_value": 150, "step": 6, "sampling": "linear"}}, {"class_name": "Int", "config": {"name": "units_2", "default": null, "conditions": [], "min_value": 1, "max_value": 150, "step": 6, "sampling": "linear"}}, {"class_name": "Int", "config": {"name": "units_3", "default": null, "conditions": [], "min_value": 1, "max_value": 150, "step": 6, "sampling": "linear"}}, {"class_name": "Int", "config": {"name": "units_4", "default": null, "conditions": [], "min_value": 1, "max_value": 150, "step": 6, "sampling": "linear"}}, {"class_name": "Int", "config": {"name": "units_5", "default": null, "conditions": [], "min_value": 1, "max_value": 150, "step": 6, "sampling": "linear"}}], "values": {"activation": "tanh", "first_units": 26, "num_layers": 3, "units_0": 13, "units_1": 1, "units_2": 145, "units_3": 49, "units_4": 85, "units_5": 25, "tuner/epochs": 150, "tuner/initial_epoch": 0, "tuner/bracket": 0, "tuner/round": 0}}, "metrics": {"metrics": {"loss": {"direction": "min", "observations": [{"value": [0.5419560670852661], "step": 42}]}, "accuracy": {"direction": "max", "observations": [{"value": [0.7372881174087524], "step": 42}]}, "val_loss": {"direction": "min", "observations": [{"value": [0.5537559390068054], "step": 42}]}, "val_accuracy": {"direction": "max", "observations": [{"value": [0.7285131216049194], "step": 42}]}}}, "score": 0.7285131216049194, "best_step": 42, "status": "COMPLETED", "message": null}