{"trial_id": "0234", "hyperparameters": {"space": [{"class_name": "Choice", "config": {"name": "activation", "default": "relu", "conditions": [], "values": ["relu", "tanh", "sigmoid"], "ordered": false}}, {"class_name": "Int", "config": {"name": "first_units", "default": null, "conditions": [], "min_value": 10, "max_value": 150, "step": 2, "sampling": "linear"}}, {"class_name": "Int", "config": {"name": "num_layers", "default": null, "conditions": [], "min_value": 1, "max_value": 6, "step": 1, "sampling": "linear"}}, {"class_name": "Int", "config": {"name": "units_0", "default": null, "conditions": [], "min_value": 1, "max_value": 150, "step": 6, "sampling": "linear"}}, {"class_name": "Int", "config": {"name": "units_1", "default": null, "conditions": [], "min_value": 1, "max_value": 150, "step": 6, "sampling": "linear"}}, {"class_name": "Int", "config": {"name": "units_2", "default": null, "conditions": [], "min_value": 1, "max_value": 150, "step": 6, "sampling": "linear"}}, {"class_name": "Int", "config": {"name": "units_3", "default": null, "conditions": [], "min_value": 1, "max_value": 150, "step": 6, "sampling": "linear"}}, {"class_name": "Int", "config": {"name": "units_4", "default": null, "conditions": [], "min_value": 1, "max_value": 150, "step": 6, "sampling": "linear"}}, {"class_name": "Int", "config": {"name": "units_5", "default": null, "conditions": [], "min_value": 1, "max_value": 150, "step": 6, "sampling": "linear"}}], "values": {"activation": "sigmoid", "first_units": 118, "num_layers": 5, "units_0": 49, "units_1": 49, "units_2": 37, "units_3": 19, "units_4": 55, "units_5": 85, "tuner/epochs": 6, "tuner/initial_epoch": 0, "tuner/bracket": 2, "tuner/round": 0}}, "metrics": {"metrics": {"loss": {"direction": "min", "observations": [{"value": [0.5705764889717102], "step": 5}]}, "accuracy": {"direction": "max", "observations": [{"value": [0.7320789694786072], "step": 5}]}, "val_loss": {"direction": "min", "observations": [{"value": [0.5798093676567078], "step": 5}]}, "val_accuracy": {"direction": "max", "observations": [{"value": [0.7269970774650574], "step": 5}]}}}, "score": 0.7269970774650574, "best_step": 5, "status": "COMPLETED", "message": null}