{"trial_id": "0471", "hyperparameters": {"space": [{"class_name": "Choice", "config": {"name": "activation", "default": "relu", "conditions": [], "values": ["relu", "tanh", "sigmoid"], "ordered": false}}, {"class_name": "Int", "config": {"name": "first_units", "default": null, "conditions": [], "min_value": 10, "max_value": 100, "step": 2, "sampling": "linear"}}, {"class_name": "Int", "config": {"name": "num_layers", "default": null, "conditions": [], "min_value": 1, "max_value": 4, "step": 1, "sampling": "linear"}}, {"class_name": "Int", "config": {"name": "units_0", "default": null, "conditions": [], "min_value": 10, "max_value": 100, "step": 6, "sampling": "linear"}}, {"class_name": "Int", "config": {"name": "units_1", "default": null, "conditions": [], "min_value": 10, "max_value": 100, "step": 6, "sampling": "linear"}}, {"class_name": "Int", "config": {"name": "units_2", "default": null, "conditions": [], "min_value": 10, "max_value": 100, "step": 6, "sampling": "linear"}}, {"class_name": "Int", "config": {"name": "units_3", "default": null, "conditions": [], "min_value": 10, "max_value": 100, "step": 6, "sampling": "linear"}}], "values": {"activation": "tanh", "first_units": 34, "num_layers": 2, "units_0": 100, "units_1": 64, "units_2": 40, "units_3": 52, "tuner/epochs": 100, "tuner/initial_epoch": 8, "tuner/bracket": 1, "tuner/round": 1, "tuner/trial_id": "0465"}}, "metrics": {"metrics": {"loss": {"direction": "min", "observations": [{"value": [0.5461104512214661], "step": 4}]}, "accuracy": {"direction": "max", "observations": [{"value": [0.7341393232345581], "step": 4}]}, "val_loss": {"direction": "min", "observations": [{"value": [0.5508991479873657], "step": 4}]}, "val_accuracy": {"direction": "max", "observations": [{"value": [0.7290962338447571], "step": 4}]}}}, "score": 0.7290962338447571, "best_step": 4, "status": "COMPLETED", "message": null}